mcp_stdio_toolbox/__init__.py
mcp_stdio_toolbox/config_loader.py
mcp_stdio_toolbox/server.py
mcp_stdio_toolbox/subprocess_runner.py
mcp_stdio_toolbox/tool_registry.py
mcp_stdio_toolbox-0.1.0.dist-info/METADATA
mcp_stdio_toolbox-0.1.0.dist-info/WHEEL
mcp_stdio_toolbox-0.1.0.dist-info/entry_points.txt
mcp_stdio_toolbox-0.1.0.dist-info/licenses/LICENSE
mcp_stdio_toolbox-0.1.0.dist-info/RECORD
