Metadata-Version: 2.4
Name: mcp-stdio-toolbox
Version: 0.1.0
Summary: A universal MCP server for wrapping CLI tools as MCP tools - stable alternative to experimental MCP implementations
Project-URL: Homepage, https://github.com/yingchuan/mcp-stdio-toolbox
Project-URL: Repository, https://github.com/yingchuan/mcp-stdio-toolbox
Project-URL: Issues, https://github.com/yingchuan/mcp-stdio-toolbox/issues
Project-URL: Documentation, https://github.com/yingchuan/mcp-stdio-toolbox#readme
Author-email: Richard Chen <yingchuan.chen.2007@gmail.com>
License: MIT License
License-File: LICENSE
Keywords: ai-integration,automation,claude,cli-tools,codex,gpt,mcp,model-context-protocol,openai,toolbox
Classifier: Development Status :: 4 - Beta
Classifier: Intended Audience :: Developers
Classifier: License :: OSI Approved :: MIT License
Classifier: Operating System :: OS Independent
Classifier: Programming Language :: Python :: 3
Classifier: Programming Language :: Python :: 3.12
Classifier: Programming Language :: Python :: 3.13
Classifier: Topic :: Scientific/Engineering :: Artificial Intelligence
Classifier: Topic :: Software Development :: Libraries :: Python Modules
Classifier: Topic :: System :: Shells
Classifier: Topic :: Utilities
Requires-Python: >=3.12
Requires-Dist: click>=8.0.0
Requires-Dist: mcp>=1.0.0
Requires-Dist: pyyaml>=6.0
Provides-Extra: dev
Requires-Dist: pytest-asyncio>=0.21.0; extra == 'dev'
Requires-Dist: pytest-cov>=4.0.0; extra == 'dev'
Requires-Dist: pytest>=7.0.0; extra == 'dev'
Requires-Dist: ruff>=0.1.0; extra == 'dev'
